MDI/Builder.py
MDI/DataFrames.py
MDI/Formatters.py
MDI/ModelCheck.py
MDI/ModelFormatters.py
MDI/PlotSeries.py
MDI/Reporting.py
MDI/Solver.py
MDI/Utils.py
MDI/YAMLLoader.py
MDI/__init__.py
MDI/ConnectionBar/ConnectionBarBuilder.py
MDI/ConnectionBar/ConnectionBarConstraints.py
MDI/ConnectionBar/ConnectionBarDataTypes.py
MDI/ConnectionBar/ConnectionBarEquations.py
MDI/ConnectionBar/ConnectionBarVars.py
MDI/ConnectionBar/__init__.py
MDI/Generator/GeneratorBuilder.py
MDI/Generator/GeneratorConstraints.py
MDI/Generator/GeneratorDataTypes.py
MDI/Generator/GeneratorEquations.py
MDI/Generator/GeneratorObjectives.py
MDI/Generator/GeneratorVars.py
MDI/Generator/__init__.py
MDI/Storage/StorageBuilder.py
MDI/Storage/StorageConstraints.py
MDI/Storage/StorageDataTypes.py
MDI/Storage/StorageEquations.py
MDI/Storage/StorageObjective.py
MDI/Storage/StorageVars.py
MDI/Storage/__init__.py
MDI/TransmissionLine/TransmissionLineBuilder.py
MDI/TransmissionLine/TransmissionLineConstraints.py
MDI/TransmissionLine/TransmissionLineDataTypes.py
MDI/TransmissionLine/TransmissionLineEquations.py
MDI/TransmissionLine/TransmissionLineVars.py
MDI/TransmissionLine/__init__.py
MDI/cli/__init__.py
MDI/cli/cli.py
MDI/cli/plot_cli.py
NaivePyDECOMP/Builder.py
NaivePyDECOMP/BuilderPDDD.py
NaivePyDECOMP/DataFrames.py
NaivePyDECOMP/Formatters.py
NaivePyDECOMP/ModelCheck.py
NaivePyDECOMP/ModelFormatters.py
NaivePyDECOMP/PDDDMergeModels.py
NaivePyDECOMP/PlotSeries.py
NaivePyDECOMP/Reporting.py
NaivePyDECOMP/Solver.py
NaivePyDECOMP/SolverPDDD.py
NaivePyDECOMP/Utils.py
NaivePyDECOMP/YAMLLoader.py
NaivePyDECOMP/__init__.py
NaivePyDECOMP/ConnectionBar/ConnectionBarBuilder.py
NaivePyDECOMP/ConnectionBar/ConnectionBarConstraints.py
NaivePyDECOMP/ConnectionBar/ConnectionBarDataTypes.py
NaivePyDECOMP/ConnectionBar/ConnectionBarEquations.py
NaivePyDECOMP/ConnectionBar/ConnectionBarVars.py
NaivePyDECOMP/ConnectionBar/__init__.py
NaivePyDECOMP/HydraulicGenerator/HydraulicConstraints.py
naivepydessem-0.1.4.dist-info/licenses/LICENSE
naivepydessem-0.1.4.dist-info/METADATA
naivepydessem-0.1.4.dist-info/WHEEL
naivepydessem-0.1.4.dist-info/entry_points.txt
naivepydessem-0.1.4.dist-info/top_level.txt
naivepydessem-0.1.4.dist-info/RECORD
