Metadata-Version: 2.4
Name: naivepydessem
Version: 0.1.4
Summary: A modular and pedagogical framework for power system operation and expansion planning using Pyomo (DESSEM, DECOMP, MDI-like solvers)
Home-page: https://github.com/superflanker/NaivePyDESSEM
Author: Augusto Mathias Adams
Author-email: Augusto Mathias Adams <augusto.adams@ufpr.br>
License: GPL-3.0
Project-URL: Homepage, https://github.com/superflanker/NaivePyDESSEM
Project-URL: Repository, https://github.com/superflanker/NaivePyDESSEM
Project-URL: Documentation, https://superflanker.github.io/NaivePyDESSEM/
Project-URL: Issues, https://github.com/superflanker/NaivePyDESSEM/issues
Keywords: pyomo,energy-planning,hydrothermal,power-systems,optimization,decomp,dessem,mdi
Classifier: Programming Language :: Python :: 3
Classifier: License :: OSI Approved :: GNU General Public License v3 (GPLv3)
Classifier: Operating System :: OS Independent
Classifier: Topic :: Scientific/Engineering
Classifier: Topic :: Scientific/Engineering :: Mathematics
Classifier: Intended Audience :: Education
Classifier: Intended Audience :: Science/Research
Requires-Python: >=3.9
License-File: LICENSE
Requires-Dist: colorama>=0.4.6
Requires-Dist: matplotlib>=3.10.5
Requires-Dist: numpy>=2.2.6
Requires-Dist: scipy>=1.15.3
Requires-Dist: pandas>=2.3.2
Requires-Dist: pyomo>=6.9.3
Requires-Dist: PyYAML>=6.0.2
Provides-Extra: docs
Requires-Dist: sphinx>=7.2; extra == "docs"
Requires-Dist: myst-parser>=2.0; extra == "docs"
Provides-Extra: solvers
Requires-Dist: highspy>=1.11.0; extra == "solvers"
Requires-Dist: gurobipy>=12.0.3; extra == "solvers"
Requires-Dist: glpk>=0.4.8; extra == "solvers"
Requires-Dist: cplex>=22.1.2.0; extra == "solvers"
Requires-Dist: cyipopt>=1.6.1; extra == "solvers"
Requires-Dist: docplex>=2.30.251; extra == "solvers"
Provides-Extra: dev
Requires-Dist: pytest>=8.3; extra == "dev"
Requires-Dist: ruff>=0.5.0; extra == "dev"
Requires-Dist: black>=24.10.0; extra == "dev"
Requires-Dist: pre-commit>=3.8.0; extra == "dev"
Dynamic: license-file
